Workbook
Name Slicer_CANAL_VINCULACION: #N/A
Name Slicer_TIPO_PERSONA: #N/A

Sheet MATRIZ_CLIENTES
A1: ID_CLIENTE | B1: TIPO_PERSONA | C1: SECTOR_ACTIVIDAD | D1: ANTIGUEDAD_ENTIDAD_AÑOS | E1: PEP | F1: FPADM | G1: BENEFICIARIO_FINAL | H1: PUNTAJE_CLIENTE | I1: PUNTAJE_CLIENTE_PONDERADO | J1: TIPO_PRODUCTO | K1: COMPLEJIDAD_PRODUCTO | L1: PUNTAJE_PRODUCTO_PONDERADO | M1: CANAL_VINCULACION | N1: PUNTAJE_CANAL_PONDERADO | O1: JURISDICCION | P1: PUNTAJE_GEOGRAFICO_PONDERADO | Q1: PUNTAJE_TOTAL | R1: ESCALONAMIENTO_AUTOMATICO | S1: NIVEL_RIESGO_FINAL | T1: DILIGENCIA_APLICABLE | U1: COLOR_RIESGO | V1: OBSERVACIONES
A2: CLI-001 | B2: Humana | C2: Empleado en relación de dependencia | D2: 2 | E2: No | F2: Sin antecedentes | G2: Identificado | H2: =AVERAGE(VLOOKUP(E2,ESCALA_PUNTAJE!$H$2:$I$5,2,FALSE),VLOOKUP(F2,ESCALA_PUNTAJE!$H$7:$I$9,2,FALSE),VLOOKUP(G2,ESCALA_PUNTAJE!$H$11:$I$13,2,FALSE)) -> 1 | I2: =H2*0.35 -> 0.35 | J2: Caja de ahorro en pesos, cuenta sueldo | K2: Baja | L2: =AVERAGE(VLOOKUP(J2,ESCALA_PUNTAJE!$J$2:$K$4,2,FALSE),VLOOKUP(K2,ESCALA_PUNTAJE!$J$6:$K$8,2,FALSE))*0.2 -> 0.2 | M2: Presencial | N2: =VLOOKUP(M2,ESCALA_PUNTAJE!$M$2:$N$4,2,FALSE)*0.15 -> 0.15 | O2: CABA | P2: =VLOOKUP(O2,ESCALA_PUNTAJE!$M$6:$N$11,2,FALSE)*0.3 -> 0.3 | Q2: =I2+L2+N2+P2 -> 1 | R2: =IF(OR(E2<>"No",F2="Coincidencia lista FPADM",G2="No identificado"),"SÍ / ALTO AUTOMÁTICO","No aplica") -> No aplica | S2: =IF(R2="SÍ / ALTO AUTOMÁTICO","ALTO",IF(Q2<=1.6,"BAJO",IF(Q2<=2.3,"MEDIO","ALTO")) ) -> BAJO | T2: =IF(S2="BAJO","Simplificada",IF(S2="MEDIO","Media","Reforzada")) -> Simplificada | V2: =IF(R2="SÍ / ALTO AUTOMÁTICO","Escalonamiento automático: revisar DD Reforzada","")
A3: CLI-002 | B3: Humana | C3: Empleado en relación de dependencia | D3: 1 | E3: No | F3: Sin antecedentes | G3: Identificado | H3: =AVERAGE(VLOOKUP(E3,ESCALA_PUNTAJE!$H$2:$I$5,2,FALSE),VLOOKUP(F3,ESCALA_PUNTAJE!$H$7:$I$9,2,FALSE),VLOOKUP(G3,ESCALA_PUNTAJE!$H$11:$I$13,2,FALSE)) -> 1 | I3: =H3*0.35 -> 0.35 | J3: Caja de ahorro en pesos, cuenta sueldo | K3: Baja | L3: =AVERAGE(VLOOKUP(J3,ESCALA_PUNTAJE!$J$2:$K$4,2,FALSE),VLOOKUP(K3,ESCALA_PUNTAJE!$J$6:$K$8,2,FALSE))*0.2 -> 0.2 | M3: Presencial | N3: =VLOOKUP(M3,ESCALA_PUNTAJE!$M$2:$N$4,2,FALSE)*0.15 -> 0.15 | O3: CABA | P3: =VLOOKUP(O3,ESCALA_PUNTAJE!$M$6:$N$11,2,FALSE)*0.3 -> 0.3 | Q3: =I3+L3+N3+P3 -> 1 | R3: =IF(OR(E3<>"No",F3="Coincidencia lista FPADM",G3="No identificado"),"SÍ / ALTO AUTOMÁTICO","No aplica") -> No aplica | S3: =IF(R3="SÍ / ALTO AUTOMÁTICO","ALTO",IF(Q3<=1.6,"BAJO",IF(Q3<=2.3,"MEDIO","ALTO")) ) -> BAJO | T3: =IF(S3="BAJO","Simplificada",IF(S3="MEDIO","Media","Reforzada")) -> Simplificada | V3: =IF(R3="SÍ / ALTO AUTOMÁTICO","Escalonamiento automático: revisar DD Reforzada","")
A4: CLI-003 | B4: Humana | C4: Empleado en relación de dependencia | D4: 5 | E4: No | F4: Sin antecedentes | G4: Identificado | H4: =AVERAGE(VLOOKUP(E4,ESCALA_PUNTAJE!$H$2:$I$5,2,FALSE),VLOOKUP(F4,ESCALA_PUNTAJE!$H$7:$I$9,2,FALSE),VLOOKUP(G4,ESCALA_PUNTAJE!$H$11:$I$13,2,FALSE)) -> 1 | I4: =H4*0.35 -> 0.35 | J4: Caja de ahorro en pesos, cuenta sueldo | K4: Baja | L4: =AVERAGE(VLOOKUP(J4,ESCALA_PUNTAJE!$J$2:$K$4,2,FALSE),VLOOKUP(K4,ESCALA_PUNTAJE!$J$6:$K$8,2,FALSE))*0.2 -> 0.2 | M4: Presencial | N4: =VLOOKUP(M4,ESCALA_PUNTAJE!$M$2:$N$4,2,FALSE)*0.15 -> 0.15 | O4: CABA | P4: =VLOOKUP(O4,ESCALA_PUNTAJE!$M$6:$N$11,2,FALSE)*0.3 -> 0.3 | Q4: =I4+L4+N4+P4 -> 1 | R4: =IF(OR(E4<>"No",F4="Coincidencia lista FPADM",G4="No identificado"),"SÍ / ALTO AUTOMÁTICO","No aplica") -> No aplica | S4: =IF(R4="SÍ / ALTO AUTOMÁTICO","ALTO",IF(Q4<=1.6,"BAJO",IF(Q4<=2.3,"MEDIO","ALTO")) ) -> BAJO | T4: =IF(S4="BAJO","Simplificada",IF(S4="MEDIO","Media","Reforzada")) -> Simplificada | V4: =IF(R4="SÍ / ALTO AUTOMÁTICO","Escalonamiento automático: revisar DD Reforzada","")
A5: CLI-004 | B5: Humana | C5: Empleado en relación de dependencia | D5: 4 | E5: No | F5: Sin antecedentes | G5: Identificado | H5: =AVERAGE(VLOOKUP(E5,ESCALA_PUNTAJE!$H$2:$I$5,2,FALSE),VLOOKUP(F5,ESCALA_PUNTAJE!$H$7:$I$9,2,FALSE),VLOOKUP(G5,ESCALA_PUNTAJE!$H$11:$I$13,2,FALSE)) -> 1 | I5: =H5*0.35 -> 0.35 | J5: Caja de ahorro en pesos, cuenta sueldo | K5: Baja | L5: =AVERAGE(VLOOKUP(J5,ESCALA_PUNTAJE!$J$2:$K$4,2,FALSE),VLOOKUP(K5,ESCALA_PUNTAJE!$J$6:$K$8,2,FALSE))*0.2 -> 0.2 | M5: Presencial | N5: =VLOOKUP(M5,ESCALA_PUNTAJE!$M$2:$N$4,2,FALSE)*0.15 -> 0.15 | O5: CABA | P5: =VLOOKUP(O5,ESCALA_PUNTAJE!$M$6:$N$11,2,FALSE)*0.3 -> 0.3 | Q5: =I5+L5+N5+P5 -> 1 | R5: =IF(OR(E5<>"No",F5="Coincidencia lista FPADM",G5="No identificado"),"SÍ / ALTO AUTOMÁTICO","No aplica") -> No aplica | S5: =IF(R5="SÍ / ALTO AUTOMÁTICO","ALTO",IF(Q5<=1.6,"BAJO",IF(Q5<=2.3,"MEDIO","ALTO")) ) -> BAJO | T5: =IF(S5="BAJO","Simplificada",IF(S5="MEDIO","Media","Reforzada")) -> Simplificada | V5: =IF(R5="SÍ / ALTO AUTOMÁTICO","Escalonamiento automático: revisar DD Reforzada","")
A6: CLI-005 | B6: Humana | C6: Empleado en relación de dependencia | D6: 4 | E6: No | F6: Sin antecedentes | G6: Identificado | H6: =AVERAGE(VLOOKUP(E6,ESCALA_PUNTAJE!$H$2:$I$5,2,FALSE),VLOOKUP(F6,ESCALA_PUNTAJE!$H$7:$I$9,2,FALSE),VLOOKUP(G6,ESCALA_PUNTAJE!$H$11:$I$13,2,FALSE)) -> 1 | I6: =H6*0.35 -> 0.35 | J6: Caja de ahorro en pesos, cuenta sueldo | K6: Baja | L6: =AVERAGE(VLOOKUP(J6,ESCALA_PUNTAJE!$J$2:$K$4,2,FALSE),VLOOKUP(K6,ESCALA_PUNTAJE!$J$6:$K$8,2,FALSE))*0.2 -> 0.2 | M6: Presencial | N6: =VLOOKUP(M6,ESCALA_PUNTAJE!$M$2:$N$4,2,FALSE)*0.15 -> 0.15 | O6: CABA | P6: =VLOOKUP(O6,ESCALA_PUNTAJE!$M$6:$N$11,2,FALSE)*0.3 -> 0.3 | Q6: =I6+L6+N6+P6 -> 1 | R6: =IF(OR(E6<>"No",F6="Coincidencia lista FPADM",G6="No identificado"),"SÍ / ALTO AUTOMÁTICO","No aplica") -> No aplica | S6: =IF(R6="SÍ / ALTO AUTOMÁTICO","ALTO",IF(Q6<=1.6,"BAJO",IF(Q6<=2.3,"MEDIO","ALTO")) ) -> BAJO | T6: =IF(S6="BAJO","Simplificada",IF(S6="MEDIO","Media","Reforzada")) -> Simplificada | V6: =IF(R6="SÍ / ALTO AUTOMÁTICO","Escalonamiento automático: revisar DD Reforzada","")
A7: CLI-006 | B7: Humana | C7: Empleado en relación de dependencia | D7: 3 | E7: No | F7: Sin antecedentes | G7: Identificado | H7: =AVERAGE(VLOOKUP(E7,ESCALA_PUNTAJE!$H$2:$I$5,2,FALSE),VLOOKUP(F7,ESCALA_PUNTAJE!$H$7:$I$9,2,FALSE),VLOOKUP(G7,ESCALA_PUNTAJE!$H$11:$I$13,2,FALSE)) -> 1 | I7: =H7*0.35 -> 0.35 | J7: Caja de ahorro en pesos, cuenta sueldo | K7: Baja | L7: =AVERAGE(VLOOKUP(J7,ESCALA_PUNTAJE!$J$2:$K$4,2,FALSE),VLOOKUP(K7,ESCALA_PUNTAJE!$J$6:$K$8,2,FALSE))*0.2 -> 0.2 | M7: Presencial | N7: =VLOOKUP(M7,ESCALA_PUNTAJE!$M$2:$N$4,2,FALSE)*0.15 -> 0.15 | O7: CABA | P7: =VLOOKUP(O7,ESCALA_PUNTAJE!$M$6:$N$11,2,FALSE)*0.3 -> 0.3 | Q7: =I7+L7+N7+P7 -> 1 | R7: =IF(OR(E7<>"No",F7="Coincidencia lista FPADM",G7="No identificado"),"SÍ / ALTO AUTOMÁTICO","No aplica") -> No aplica | S7: =IF(R7="SÍ / ALTO AUTOMÁTICO","ALTO",IF(Q7<=1.6,"BAJO",IF(Q7<=2.3,"MEDIO","ALTO")) ) -> BAJO | T7: =IF(S7="BAJO","Simplificada",IF(S7="MEDIO","Media","Reforzada")) -> Simplificada | V7: =IF(R7="SÍ / ALTO AUTOMÁTICO","Escalonamiento automático: revisar DD Reforzada","")
A8: CLI-007 | B8: Humana | C8: Empleado en relación de dependencia | D8: 2 | E8: No | F8: Sin antecedentes | G8: Identificado | H8: =AVERAGE(VLOOKUP(E8,ESCALA_PUNTAJE!$H$2:$I$5,2,FALSE),VLOOKUP(F8,ESCALA_PUNTAJE!$H$7:$I$9,2,FALSE),VLOOKUP(G8,ESCALA_PUNTAJE!$H$11:$I$13,2,FALSE)) -> 1 | I8: =H8*0.35 -> 0.35 | J8: Caja de ahorro en pesos, cuenta sueldo | K8: Baja | L8: =AVERAGE(VLOOKUP(J8,ESCALA_PUNTAJE!$J$2:$K$4,2,FALSE),VLOOKUP(K8,ESCALA_PUNTAJE!$J$6:$K$8,2,FALSE))*0.2 -> 0.2 | M8: Presencial | N8: =VLOOKUP(M8,ESCALA_PUNTAJE!$M$2:$N$4,2,FALSE)*0.15 -> 0.15 | O8: CABA | P8: =VLOOKUP(O8,ESCALA_PUNTAJE!$M$6:$N$11,2,FALSE)*0.3 -> 0.3 | Q8: =I8+L8+N8+P8 -> 1 | R8: =IF(OR(E8<>"No",F8="Coincidencia lista FPADM",G8="No identificado"),"SÍ / ALTO AUTOMÁTICO","No aplica") -> No aplica | S8: =IF(R8="SÍ / ALTO AUTOMÁTICO","ALTO",IF(Q8<=1.6,"BAJO",IF(Q8<=2.3,"MEDIO","ALTO")) ) -> BAJO | T8: =IF(S8="BAJO","Simplificada",IF(S8="MEDIO","Media","Reforzada")) -> Simplificada | V8: =IF(R8="SÍ / ALTO AUTOMÁTICO","Escalonamiento automático: revisar DD Reforzada","")
A9: CLI-008 | B9: Humana | C9: Empleado en relación de dependencia | D9: 9 | E9: No | F9: Sin antecedentes | G9: Identificado | H9: =AVERAGE(VLOOKUP(E9,ESCALA_PUNTAJE!$H$2:$I$5,2,FALSE),VLOOKUP(F9,ESCALA_PUNTAJE!$H$7:$I$9,2,FALSE),VLOOKUP(G9,ESCALA_PUNTAJE!$H$11:$I$13,2,FALSE)) -> 1 | I9: =H9*0.35 -> 0.35 | J9: Caja de ahorro en pesos, cuenta sueldo | K9: Baja | L9: =AVERAGE(VLOOKUP(J9,ESCALA_PUNTAJE!$J$2:$K$4,2,FALSE),VLOOKUP(K9,ESCALA_PUNTAJE!$J$6:$K$8,2,FALSE))*0.2 -> 0.2 | M9: Presencial | N9: =VLOOKUP(M9,ESCALA_PUNTAJE!$M$2:$N$4,2,FALSE)*0.15 -> 0.15 | O9: CABA | P9: =VLOOKUP(O9,ESCALA_PUNTAJE!$M$6:$N$11,2,FALSE)*0.3 -> 0.3 | Q9: =I9+L9+N9+P9 -> 1 | R9: =IF(OR(E9<>"No",F9="Coincidencia lista FPADM",G9="No identificado"),"SÍ / ALTO AUTOMÁTICO","No aplica") -> No aplica | S9: =IF(R9="SÍ / ALTO AUTOMÁTICO","ALTO",IF(Q9<=1.6,"BAJO",IF(Q9<=2.3,"MEDIO","ALTO")) ) -> BAJO | T9: =IF(S9="BAJO","Simplificada",IF(S9="MEDIO","Media","Reforzada")) -> Simplificada | V9: =IF(R9="SÍ / ALTO AUTOMÁTICO","Escalonamiento automático: revisar DD Reforzada","")
A10: CLI-009 | B10: Humana | C10: Empleado en relación de dependencia | D10: 2 | E10: No | F10: Sin antecedentes | G10: Identificado | H10: =AVERAGE(VLOOKUP(E10,ESCALA_PUNTAJE!$H$2:$I$5,2,FALSE),VLOOKUP(F10,ESCALA_PUNTAJE!$H$7:$I$9,2,FALSE),VLOOKUP(G10,ESCALA_PUNTAJE!$H$11:$I$13,2,FALSE)) -> 1 | I10: =H10*0.35 -> 0.35 | J10: Caja de ahorro en pesos, cuenta sueldo | K10: Baja | L10: =AVERAGE(VLOOKUP(J10,ESCALA_PUNTAJE!$J$2:$K$4,2,FALSE),VLOOKUP(K10,ESCALA_PUNTAJE!$J$6:$K$8,2,FALSE))*0.2 -> 0.2 | M10: Presencial | N10: =VLOOKUP(M10,ESCALA_PUNTAJE!$M$2:$N$4,2,FALSE)*0.15 -> 0.15 | O10: CABA | P10: =VLOOKUP(O10,ESCALA_PUNTAJE!$M$6:$N$11,2,FALSE)*0.3 -> 0.3 | Q10: =I10+L10+N10+P10 -> 1 | R10: =IF(OR(E10<>"No",F10="Coincidencia lista FPADM",G10="No identificado"),"SÍ / ALTO AUTOMÁTICO","No aplica") -> No aplica | S10: =IF(R10="SÍ / ALTO AUTOMÁTICO","ALTO",IF(Q10<=1.6,"BAJO",IF(Q10<=2.3,"MEDIO","ALTO")) ) -> BAJO | T10: =IF(S10="BAJO","Simplificada",IF(S10="MEDIO","Media","Reforzada")) -> Simplificada | V10: =IF(R10="SÍ / ALTO AUTOMÁTICO","Escalonamiento automático: revisar DD Reforzada","")
A11: CLI-010 | B11: Humana | C11: Empleado en relación de dependencia | D11: 10 | E11: No | F11: Sin antecedentes | G11: Identificado | H11: =AVERAGE(VLOOKUP(E11,ESCALA_PUNTAJE!$H$2:$I$5,2,FALSE),VLOOKUP(F11,ESCALA_PUNTAJE!$H$7:$I$9,2,FALSE),VLOOKUP(G11,ESCALA_PUNTAJE!$H$11:$I$13,2,FALSE)) -> 1 | I11: =H11*0.35 -> 0.35 | J11: Caja de ahorro en pesos, cuenta sueldo | K11: Baja | L11: =AVERAGE(VLOOKUP(J11,ESCALA_PUNTAJE!$J$2:$K$4,2,FALSE),VLOOKUP(K11,ESCALA_PUNTAJE!$J$6:$K$8,2,FALSE))*0.2 -> 0.2 | M11: Presencial | N11: =VLOOKUP(M11,ESCALA_PUNTAJE!$M$2:$N$4,2,FALSE)*0.15 -> 0.15 | O11: CABA | P11: =VLOOKUP(O11,ESCALA_PUNTAJE!$M$6:$N$11,2,FALSE)*0.3 -> 0.3 | Q11: =I11+L11+N11+P11 -> 1 | R11: =IF(OR(E11<>"No",F11="Coincidencia lista FPADM",G11="No identificado"),"SÍ / ALTO AUTOMÁTICO","No aplica") -> No aplica | S11: =IF(R11="SÍ / ALTO AUTOMÁTICO","ALTO",IF(Q11<=1.6,"BAJO",IF(Q11<=2.3,"MEDIO","ALTO")) ) -> BAJO | T11: =IF(S11="BAJO","Simplificada",IF(S11="MEDIO","Media","Reforzada")) -> Simplificada | V11: =IF(R11="SÍ / ALTO AUTOMÁTICO","Escalonamiento automático: revisar DD Reforzada","")
A12: CLI-011 | B12: Humana | C12: Empleado en relación de dependencia | D12: 7 | E12: No | F12: Sin antecedentes | G12: Identificado | H12: =AVERAGE(VLOOKUP(E12,ESCALA_PUNTAJE!$H$2:$I$5,2,FALSE),VLOOKUP(F12,ESCALA_PUNTAJE!$H$7:$I$9,2,FALSE),VLOOKUP(G12,ESCALA_PUNTAJE!$H$11:$I$13,2,FALSE)) -> 1 | I12: =H12*0.35 -> 0.35 | J12: Caja de ahorro en pesos, cuenta sueldo | K12: Baja | L12: =AVERAGE(VLOOKUP(J12,ESCALA_PUNTAJE!$J$2:$K$4,2,FALSE),VLOOKUP(K12,ESCALA_PUNTAJE!$J$6:$K$8,2,FALSE))*0.2 -> 0.2 | M12: Presencial | N12: =VLOOKUP(M12,ESCALA_PUNTAJE!$M$2:$N$4,2,FALSE)*0.15 -> 0.15 | O12: CABA | P12: =VLOOKUP(O12,ESCALA_PUNTAJE!$M$6:$N$11,2,FALSE)*0.3 -> 0.3 | Q12: =I12+L12+N12+P12 -> 1 | R12: =IF(OR(E12<>"No",F12="Coincidencia lista FPADM",G12="No identificado"),"SÍ / ALTO AUTOMÁTICO","No aplica") -> No aplica | S12: =IF(R12="SÍ / ALTO AUTOMÁTICO","ALTO",IF(Q12<=1.6,"BAJO",IF(Q12<=2.3,"MEDIO","ALTO")) ) -> BAJO | T12: =IF(S12="BAJO","Simplificada",IF(S12="MEDIO","Media","Reforzada")) -> Simplificada | V12: =IF(R12="SÍ / ALTO AUTOMÁTICO","Escalonamiento automático: revisar DD Reforzada","")
A13: CLI-012 | B13: Humana | C13: Empleado en relación de dependencia | D13: 1 | E13: No | F13: Sin antecedentes | G13: Identificado | H13: =AVERAGE(VLOOKUP(E13,ESCALA_PUNTAJE!$H$2:$I$5,2,FALSE),VLOOKUP(F13,ESCALA_PUNTAJE!$H$7:$I$9,2,FALSE),VLOOKUP(G13,ESCALA_PUNTAJE!$H$11:$I$13,2,FALSE)) -> 1 | I13: =H13*0.35 -> 0.35 | J13: Caja de ahorro en pesos, cuenta sueldo | K13: Baja | L13: =AVERAGE(VLOOKUP(J13,ESCALA_PUNTAJE!$J$2:$K$4,2,FALSE),VLOOKUP(K13,ESCALA_PUNTAJE!$J$6:$K$8,2,FALSE))*0.2 -> 0.2 | M13: Presencial | N13: =VLOOKUP(M13,ESCALA_PUNTAJE!$M$2:$N$4,2,FALSE)*0.15 -> 0.15 | O13: CABA | P13: =VLOOKUP(O13,ESCALA_PUNTAJE!$M$6:$N$11,2,FALSE)*0.3 -> 0.3 | Q13: =I13+L13+N13+P13 -> 1 | R13: =IF(OR(E13<>"No",F13="Coincidencia lista FPADM",G13="No identificado"),"SÍ / ALTO AUTOMÁTICO","No aplica") -> No aplica | S13: =IF(R13="SÍ / ALTO AUTOMÁTICO","ALTO",IF(Q13<=1.6,"BAJO",IF(Q13<=2.3,"MEDIO","ALTO")) ) -> BAJO | T13: =IF(S13="BAJO","Simplificada",IF(S13="MEDIO","Media","Reforzada")) -> Simplificada | V13: =IF(R13="SÍ / ALTO AUTOMÁTICO","Escalonamiento automático: revisar DD Reforzada","")
... A51: CLI-050 | B51: Jurídica Simple | C51: Actividad variada | D51: 6 | E51: No | F51: Sin antecedentes | G51: Parcial | H51: =AVERAGE(VLOOKUP(E51,ESCALA_PUNTAJE!$H$2:$I$5,2,FALSE),VLOOKUP(F51,ESCALA_PUNTAJE!$H$7:$I$9,2,FALSE),VLOOKUP(G51,ESCALA_PUNTAJE!$H$11:$I$13,2,FALSE)) -> 1.3333333 | I51: =H51*0.35 -> 0.46666667 | J51: Transferencias internacionales, productos de inversión, fideicomisos financieros | K51: Alta | L51: =AVERAGE(VLOOKUP(J51,ESCALA_PUNTAJE!$J$2:$K$4,2,FALSE),VLOOKUP(K51,ESCALA_PUNTAJE!$J$6:$K$8,2,FALSE))*0.2 -> 0.6 | M51: Digital | N51: =VLOOKUP(M51,ESCALA_PUNTAJE!$M$2:$N$4,2,FALSE)*0.15 -> 0.45 | O51: Jurisdicción GAFI | P51: =VLOOKUP(O51,ESCALA_PUNTAJE!$M$6:$N$11,2,FALSE)*0.3 -> 0.9 | Q51: =I51+L51+N51+P51 -> 2.4166667 | R51: =IF(OR(E51<>"No",F51="Coincidencia lista FPADM",G51="No identificado"),"SÍ / ALTO AUTOMÁTICO","No aplica") -> No aplica | S51: =IF(R51="SÍ / ALTO AUTOMÁTICO","ALTO",IF(Q51<=1.6,"BAJO",IF(Q51<=2.3,"MEDIO","ALTO")) ) -> ALTO | T51: =IF(S51="BAJO","Simplificada",IF(S51="MEDIO","Media","Reforzada")) -> Reforzada | V51: =IF(R51="SÍ / ALTO AUTOMÁTICO","Escalonamiento automático: revisar DD Reforzada","")

Sheet ESCALA_PUNTAJE
H1: PEP | I1: PEP | J1: PRODUCT | K1: PRODUCT | M1: CANAL | N1: CANAL
H2: No | I2: 1 | J2: Caja de ahorro en pesos, cuenta sueldo | K2: 1 | M2: Presencial | N2: 1
A3: FACTOR CLIENTE | H3: PEP Nacional Bajo | I3: 2 | J3: Cuenta corriente, crédito personal, tarjeta de crédito | K3: 2 | M3: Mixto | N3: 2
A4: Subfactor | B4: Valor 1 - Bajo | C4: Valor 2 - Medio | D4: Valor 3 - Alto | H4: PEP Nacional Alto | I4: 3 | J4: Transferencias internacionales, productos de inversión, fideicomisos financieros | K4: 3 | M4: Digital | N4: 3
A5: Tipo de persona | B5: Humana, sin estructura jurídica compleja | C5: Jurídica simple (sociedad unipersonal, SAS) | D5: Jurídica compleja (SA con accionistas en el exterior, fideicomiso, fundación) | H5: PEP Extranjero | I5: 3 | J5: COMPL | K5: COMPL | M5: JURIS | N5: JURIS
A6: Condición PEP | B6: No es PEP | C6: PEP nacional de nivel bajo (funcionario municipal) | D6: PEP nacional de nivel alto o PEP extranjero | H6: FPADM | I6: FPADM | J6: Baja | K6: 1 | M6: CABA | N6: 1
A7: Condición FPADM | B7: Sin antecedentes | C7: Antecedentes menores o investigaciones sin condena | D7: Coincidencia en lista FPADM (Res. UIF N° 3/2026) | H7: Sin antecedentes | I7: 1 | J7: Media | K7: 2 | M7: Buenos Aires | N7: 1
A8: Beneficiario final identificado | B8: Identificado completamente | C8: Identificado parcialmente | D8: No identificado o identificación en trámite | H8: Antecedentes menores | I8: 2 | J8: Alta | K8: 3 | M8: Córdoba | N8: 1
A9: Fuente: Art. 4°, Res. UIF N° 14/2023 (mod. Res. 199/2024). La incorporación del subfactor FPADM responde a la ampliación del objeto normativo de LA/FT a LA/FT/FP. | H9: Coincidencia lista FPADM | I9: 3 | M9: Santa Fe | N9: 1
H10: BENEF | I10: BENEF | M10: Otra provincia/Argentina | N10: 2
H11: Identificado | I11: 1 | M11: Jurisdicción GAFI | N11: 3
H12: Parcial | I12: 2
H13: No identificado | I13: 3
A14: FACTOR PRODUCTO/SERVICIO
A15: Subfactor | B15: Valor 1 - Bajo | C15: Valor 2 - Medio | D15: Valor 3 Alto
A16: Tipo de producto | B16: Caja de ahorro en pesos, cuenta sueldo | C16: Cuenta corriente, crédito personal, tarjeta de crédito | D16: Transferencias internacionales, productos de inversión, fideicomisos financieros
A17: Complejidad del producto | B17: Sin estructuras adicionales | C17: Requiere documentación de respaldo | D17: Alta complejidad (cadena de custodios, múltiples jurisdicciones)
A20: FACTOR CANAL
A21: Canal | B21: Puntaje
A22: Presencial en sucursal con identificación completa | B22: 1
A23: Semipresencial o mixto (inicio online, firma presencial) | B23: 2
A24: 100% digital / no presencial / sin contacto directo | B24: 3
A25: Fuente: Art. 26, Res. UIF N° 14/2023 (mod. Res. 78/2025). La identificación no presencial habilitada normativamente conlleva controles adicionales que elevan el puntaje de riesgo del canal.
A28: FACTOR GEOGRAFICO
A29: Jurisdicción del cliente | B29: Puntaje
A30: CABA | B30: 1
A31: Buenos Aires | B31: 1
A32: Córdoba | B32: 1
A33: Santa Fe | B33: 1
A34: Otras provincias argentinas sin alerta específica de la UIF | B34: 2
A35: Jurisdicciones identificadas por la UIF como de mayor riesgo o incluidas en listados GAFI | B35: 3 | D35: ESCALA DE CLASIFICACION FINAL Y DEBIDA DILIGENCIA APLICABLE
A36: Fuente: Art. 4°, Res. UIF N° 14/2023.
A39: ESCALA DE CLASIFICACION FINAL Y DEBIDA DILIGENCIA APLICABLE
A40: Puntaje ponderado total | B40: Nivel de riesgo | C40: Debida diligencia aplicable | D40: Referencia normativa
A41: 1.00 — 1.60 | B41: BAJO | C41: Simplificada (hasta 12 SMVM/mes para clientes de inclusión financiera) | D41: Art. 27, Res. 14/2023 (mod. 199/2024)
A42: 1.61 — 2.30 | B42: MEDIO | C42: Media (documentación estándar completa) | D42: Art. 27, Res. 14/2023
A43: 2.31 — 3.00 | B43: ALTO | C43: Reforzada (origen de fondos + propósito + monitoreo intensificado) | D43: Art. 28, Res. 14/2023
A44: Regla de escalonamiento automático: independientemente del puntaje ponderado, todo cliente con condición de PEP activo, coincidencia en lista FPADM (Res. UIF N° 3/2026) o beneficiario final no identificado se clasifica automáticamente como ALTO y se le aplica Debida Diligencia Reforzada. La norma prevalece sobre la metodología interna.

Sheet RESUMEN_CARTERA
A3: AML & KYC
A6: Risk Monitoring & Reporting
A9: LA/FT/FP
Y21: CLIENTE | AB21: RIESGO | AE21: OBSERVACIONES | AK21: DILIGENCIA
Y25: =Graficos!U22 -> CLI-050 | AB25: =Graficos!X22 -> 2.4166667 | AE25: =Graficos!W22 -> 0 | AK25: =Graficos!V22 -> Reforzada
Y28: =Graficos!U23 -> CLI-049 | AB28: =Graficos!X23 -> 2.3166667 | AE28: =Graficos!W23 -> 0 | AK28: =Graficos!V23 -> Reforzada
Y31: =Graficos!U24 -> CLI-048 | AB31: =Graficos!X24 -> 2.3166667 | AE31: =Graficos!W24 -> 0 | AK31: =Graficos!V24 -> Reforzada
Y34: =Graficos!U25 -> CLI-047 | AB34: =Graficos!X25 -> 2.5333333 | AE34: =Graficos!W25 -> Escalonamiento automático: revisar DD Reforzada | AK34: =Graficos!V25 -> Reforzada
Y37: =Graficos!U26 -> CLI-042 | AB37: =Graficos!X26 -> 2.1166667 | AE37: =Graficos!W26 -> 0 | AK37: =Graficos!V26 -> Media
Y40: =Graficos!U27 -> CLI-041 | AB40: =Graficos!X27 -> 2.1166667 | AE40: =Graficos!W27 -> 0 | AK40: =Graficos!V27 -> Media
Y43: =Graficos!U28 -> CLI-039 | AB43: =Graficos!X28 -> 2.2333333 | AE43: =Graficos!W28 -> Escalonamiento automático: revisar DD Reforzada | AK43: =Graficos!V28 -> Reforzada
Y46: =Graficos!U29 -> CLI-038 | AB46: =Graficos!X29 -> 2.15 | AE46: =Graficos!W29 -> 0 | AK46: =Graficos!V29 -> Media
Y49: =Graficos!U30 -> CLI-024 | AB49: =Graficos!X30 -> 2.1166667 | AE49: =Graficos!W30 -> 0 | AK49: =Graficos!V30 -> Media
Y52: =Graficos!U31 -> CLI-023 | AB52: =Graficos!X31 -> 2.1166667 | AE52: =Graficos!W31 -> 0 | AK52: =Graficos!V31 -> Media

Sheet Graficos
A1: Clientes Riesgo BAJO | T1: NIVEL_RIESGO_FINAL | U1: BAJO
A2: =GETPIVOTDATA("ID_CLIENTE",$T$3) -> 19
T3: Count of ID_CLIENTE
A4: Clientes Riesgo MEDIO | T4: 19
A5: =GETPIVOTDATA("ID_CLIENTE",$H$13) -> 17
A7: Clientes Riesgo ALTO
A8: =GETPIVOTDATA("ID_CLIENTE",$Q$18) -> 14
A10: Total Clientes
A11: =A2+A5+A8 -> 50 | H11: NIVEL_RIESGO_FINAL | I11: MEDIO | V11: Row Labels | W11: Count of ID_CLIENTE
V12: ALTO | W12: 0.28
H13: Count of ID_CLIENTE | V13: BAJO | W13: 0.38
H14: 17 | L14: Count of ID_CLIENTE | M14: Column Labels | V14: MEDIO | W14: 0.34
L15: Row Labels | M15: Digital | N15: Mixto | O15: Presencial | P15: Grand Total | V15: Grand Total | W15: 1
L16: ALTO | M16: 5 | N16: 6 | O16: 3 | P16: 14 | Q16: NIVEL_RIESGO_FINAL | R16: ALTO
L17: BAJO | O17: 19 | P17: 19
L18: MEDIO | M18: 11 | N18: 6 | P18: 17 | Q18: Cliente Riesgo Alto
L19: Grand Total | M19: 16 | N19: 12 | O19: 22 | P19: 50 | Q19: 14 | U19: TOP 5 CLIENTES MAS RIESGOSOS
U21: ID_CLIENTE | V21: DILIGENCIA_APLICABLE | W21: OBSERVACIONES | X21: Sum of PUNTAJE_TOTAL
U22: CLI-050 | V22: Reforzada | X22: 2.4166667
U23: CLI-049 | V23: Reforzada | X23: 2.3166667
U24: CLI-048 | V24: Reforzada | X24: 2.3166667
U25: CLI-047 | V25: Reforzada | W25: Escalonamiento automático: revisar DD Reforzada | X25: 2.5333333
U26: CLI-042 | V26: Media | X26: 2.1166667
U27: CLI-041 | V27: Media | X27: 2.1166667
U28: CLI-039 | V28: Reforzada | W28: Escalonamiento automático: revisar DD Reforzada | X28: 2.2333333
U29: CLI-038 | V29: Media | X29: 2.15
U30: CLI-024 | V30: Media | X30: 2.1166667
U31: CLI-023 | V31: Media | X31: 2.1166667
U32: Grand Total | X32: 22.433333
